pysurv/__init__.py
pysurv/plot_km_curve.py
pysurv-1.0.0.dist-info/LICENSE
pysurv-1.0.0.dist-info/METADATA
pysurv-1.0.0.dist-info/WHEEL
pysurv-1.0.0.dist-info/top_level.txt
pysurv-1.0.0.dist-info/RECORD
