Metadata-Version: 2.1
Name: pysurv
Version: 1.0.0
Summary: A Python package for plotting Kaplan-Meier survival curves.
Home-page: https://github.com/pushkarmutha/PySurv
Author: Pushkar Mutha
Author-email: pushkar.mutha@outlook.com
Classifier: Programming Language :: Python :: 3
Classifier: License :: OSI Approved :: MIT License
Classifier: Operating System :: OS Independent
Classifier: Intended Audience :: Science/Research
Classifier: Topic :: Scientific/Engineering :: Bio-Informatics
Requires-Python: >=3.6
License-File: LICENSE
Requires-Dist: numpy
Requires-Dist: pandas
Requires-Dist: lifelines
Requires-Dist: matplotlib
